emotionextractor/__init__.py
emotionextractor/emotionextractor.py
emotionextractor/data/__init__.py
emotionextractor/data/data.pkl
emotionextractor/data/data_strict.pkl
EmotionExtractor-0.0.3.dist-info/LICENSE
EmotionExtractor-0.0.3.dist-info/METADATA
EmotionExtractor-0.0.3.dist-info/WHEEL
EmotionExtractor-0.0.3.dist-info/top_level.txt
EmotionExtractor-0.0.3.dist-info/RECORD
