Metadata-Version: 2.1
Name: EmotionExtractor
Version: 0.0.3
Summary: Extract Emotion Words from Text or Word Tokens
Home-page: https://github.com/riyadhctg/EmotionExtractor.git
Author: Md Riyadh
Author-email: mdriyadh@cmail.carleton.ca
Classifier: Programming Language :: Python :: 3
Classifier: License :: OSI Approved :: MIT License
Classifier: Operating System :: OS Independent
License-File: LICENSE
Requires-Dist: nltk
Requires-Dist: setuptools
Requires-Dist: wheel
